<?xml version="1.0" encoding="utf-8"?>
<search>
  
  
  
  <entry>
    <title>无题</title>
    <link href="/2024/07/08/s/s30/"/>
    <url>/2024/07/08/s/s30/</url>
    
    
    <categories>
      
      <category>文学</category>
      
      <category>现代诗</category>
      
    </categories>
    
    
    <tags>
      
      <tag>文学</tag>
      
      <tag>诗集</tag>
      
    </tags>
    
  </entry>
  
  
  
  <entry>
    <title>南乡子夜游鸡鸣寺看景阳井有感</title>
    <link href="/2024/07/08/s/s29/"/>
    <url>/2024/07/08/s/s29/</url>
    
    
    <categories>
      
      <category>文学</category>
      
      <category>诗词曲联</category>
      
    </categories>
    
    
    <tags>
      
      <tag>文学</tag>
      
      <tag>词集</tag>
      
    </tags>
    
  </entry>
  
  
  
  <entry>
    <title>音韵学简言</title>
    <link href="/2024/07/06/jx/chinese_linguistics/"/>
    <url>/2024/07/06/jx/chinese_linguistics/</url>
    
    
    <categories>
      
      <category>文学简言</category>
      
      <category>语言</category>
      
    </categories>
    
    
    <tags>
      
      <tag>文学</tag>
      
    </tags>
    
  </entry>
  
  
  
  <entry>
    <title>花烛夜</title>
    <link href="/2024/07/05/s28/"/>
    <url>/2024/07/05/s28/</url>
    
    
    <categories>
      
      <category>文学</category>
      
      <category>诗词曲联</category>
      
    </categories>
    
    
    <tags>
      
      <tag>文学</tag>
      
      <tag>诗集</tag>
      
    </tags>
    
  </entry>
  
  
  
  <entry>
    <title>古风十一（雨过新朝）</title>
    <link href="/2024/07/05/s27/"/>
    <url>/2024/07/05/s27/</url>
    
    
    <categories>
      
      <category>文学</category>
      
      <category>诗词曲联</category>
      
    </categories>
    
    
    <tags>
      
      <tag>文学</tag>
      
      <tag>诗集</tag>
      
    </tags>
    
  </entry>
  
  
  
  <entry>
    <title>集(烦躁)</title>
    <link href="/2024/07/04/s26/"/>
    <url>/2024/07/04/s26/</url>
    
    
    <categories>
      
      <category>文学</category>
      
      <category>现代诗</category>
      
    </categories>
    
    
    <tags>
      
      <tag>文学</tag>
      
      <tag>诗集</tag>
      
    </tags>
    
  </entry>
  
  
  
  <entry>
    <title>生活记事(海子重编1)</title>
    <link href="/2024/07/04/s25/"/>
    <url>/2024/07/04/s25/</url>
    
    
    <categories>
      
      <category>文学</category>
      
      <category>现代诗</category>
      
      <category>生活记事</category>
      
    </categories>
    
    
    <tags>
      
      <tag>文学</tag>
      
      <tag>诗集</tag>
      
    </tags>
    
  </entry>
  
  
  
  <entry>
    <title>生活记事(2024.6.15)</title>
    <link href="/2024/07/04/s24/"/>
    <url>/2024/07/04/s24/</url>
    
    
    <categories>
      
      <category>文学</category>
      
      <category>现代诗</category>
      
      <category>生活记事</category>
      
    </categories>
    
    
    <tags>
      
      <tag>文学</tag>
      
      <tag>诗集</tag>
      
    </tags>
    
  </entry>
  
  
  
  <entry>
    <title>生活记事(另一种)</title>
    <link href="/2024/07/04/s23/"/>
    <url>/2024/07/04/s23/</url>
    
    
    <categories>
      
      <category>文学</category>
      
      <category>现代诗</category>
      
      <category>生活记事</category>
      
    </categories>
    
    
    <tags>
      
      <tag>文学</tag>
      
      <tag>诗集</tag>
      
    </tags>
    
  </entry>
  
  
  
  <entry>
    <title>生活记事(宅家)</title>
    <link href="/2024/07/04/s22/"/>
    <url>/2024/07/04/s22/</url>
    
    
    <categories>
      
      <category>文学</category>
      
      <category>现代诗</category>
      
      <category>生活记事</category>
      
    </categories>
    
    
    <tags>
      
      <tag>文学</tag>
      
      <tag>诗集</tag>
      
    </tags>
    
  </entry>
  
  
  
  <entry>
    <title>生活记事(新)</title>
    <link href="/2024/07/04/s20/"/>
    <url>/2024/07/04/s20/</url>
    
    
    <categories>
      
      <category>文学</category>
      
      <category>现代诗</category>
      
      <category>生活记事</category>
      
    </categories>
    
    
    <tags>
      
      <tag>文学</tag>
      
      <tag>诗集</tag>
      
    </tags>
    
  </entry>
  
  
  
  <entry>
    <title>生活记事(村庄)</title>
    <link href="/2024/07/04/s21/"/>
    <url>/2024/07/04/s21/</url>
    
    
    <categories>
      
      <category>文学</category>
      
      <category>现代诗</category>
      
      <category>生活记事</category>
      
    </categories>
    
    
    <tags>
      
      <tag>文学</tag>
      
      <tag>诗集</tag>
      
    </tags>
    
  </entry>
  
  
  
  <entry>
    <title>生活记事(我)</title>
    <link href="/2024/07/04/s19/"/>
    <url>/2024/07/04/s19/</url>
    
    
    <categories>
      
      <category>文学</category>
      
      <category>现代诗</category>
      
      <category>生活记事</category>
      
    </categories>
    
    
    <tags>
      
      <tag>文学</tag>
      
      <tag>诗集</tag>
      
    </tags>
    
  </entry>
  
  
  
  <entry>
    <title>五月</title>
    <link href="/2024/06/28/s18/"/>
    <url>/2024/06/28/s18/</url>
    
    
    <categories>
      
      <category>文学</category>
      
      <category>诗词曲联</category>
      
    </categories>
    
    
    <tags>
      
      <tag>文学</tag>
      
      <tag>诗集</tag>
      
    </tags>
    
  </entry>
  
  
  
  <entry>
    <title>临江仙-五月七日碎笔</title>
    <link href="/2024/06/28/s17/"/>
    <url>/2024/06/28/s17/</url>
    
    
    <categories>
      
      <category>文学</category>
      
      <category>诗词曲联</category>
      
    </categories>
    
    
    <tags>
      
      <tag>文学</tag>
      
      <tag>词集</tag>
      
    </tags>
    
  </entry>
  
  
  
  <entry>
    <title>暮春舍中闻雨雪</title>
    <link href="/2024/06/28/s16/"/>
    <url>/2024/06/28/s16/</url>
    
    
    <categories>
      
      <category>文学</category>
      
      <category>诗词曲联</category>
      
    </categories>
    
    
    <tags>
      
      <tag>文学</tag>
      
      <tag>诗集</tag>
      
    </tags>
    
  </entry>
  
  
  
  <entry>
    <title>葬花</title>
    <link href="/2024/06/28/s15/"/>
    <url>/2024/06/28/s15/</url>
    
    
    <categories>
      
      <category>文学</category>
      
      <category>诗词曲联</category>
      
    </categories>
    
    
    <tags>
      
      <tag>文学</tag>
      
      <tag>诗集</tag>
      
    </tags>
    
  </entry>
  
  
  
  <entry>
    <title>菩萨蛮-去年燕子新回北</title>
    <link href="/2024/06/28/s14/"/>
    <url>/2024/06/28/s14/</url>
    
    
    <categories>
      
      <category>文学</category>
      
      <category>诗词曲联</category>
      
    </categories>
    
    
    <tags>
      
      <tag>文学</tag>
      
      <tag>词集</tag>
      
    </tags>
    
  </entry>
  
  
  
  <entry>
    <title>唇吻</title>
    <link href="/2024/06/27/s13/"/>
    <url>/2024/06/27/s13/</url>
    
    
    <categories>
      
      <category>文学</category>
      
      <category>现代诗</category>
      
    </categories>
    
    
    <tags>
      
      <tag>文学</tag>
      
      <tag>诗集</tag>
      
    </tags>
    
  </entry>
  
  
  
  <entry>
    <title>无题</title>
    <link href="/2024/06/27/s12/"/>
    <url>/2024/06/27/s12/</url>
    
    
    <categories>
      
      <category>文学</category>
      
      <category>现代诗</category>
      
    </categories>
    
    
    <tags>
      
      <tag>文学</tag>
      
      <tag>诗集</tag>
      
    </tags>
    
  </entry>
  
  
  
  <entry>
    <title>瓢虫记</title>
    <link href="/2024/06/27/s11/"/>
    <url>/2024/06/27/s11/</url>
    
    
    <categories>
      
      <category>文学</category>
      
      <category>现代诗</category>
      
    </categories>
    
    
    <tags>
      
      <tag>文学</tag>
      
      <tag>诗集</tag>
      
    </tags>
    
  </entry>
  
  
  
  <entry>
    <title>杞人</title>
    <link href="/2024/06/27/s10/"/>
    <url>/2024/06/27/s10/</url>
    
    
    <categories>
      
      <category>文学</category>
      
      <category>现代诗</category>
      
    </categories>
    
    
    <tags>
      
      <tag>文学</tag>
      
      <tag>诗集</tag>
      
    </tags>
    
  </entry>
  
  
  
  <entry>
    <title>渔家傲-感怀</title>
    <link href="/2024/06/27/s9/"/>
    <url>/2024/06/27/s9/</url>
    
    
    <categories>
      
      <category>文学</category>
      
      <category>诗词曲联</category>
      
    </categories>
    
    
    <tags>
      
      <tag>文学</tag>
      
      <tag>词集</tag>
      
    </tags>
    
  </entry>
  
  
  
  <entry>
    <title>人月圆-寄秋月兄</title>
    <link href="/2024/06/27/s8/"/>
    <url>/2024/06/27/s8/</url>
    
    
    <categories>
      
      <category>文学</category>
      
      <category>诗词曲联</category>
      
    </categories>
    
    
    <tags>
      
      <tag>文学</tag>
      
      <tag>词集</tag>
      
    </tags>
    
  </entry>
  
  
  
  <entry>
    <title>寒歌行</title>
    <link href="/2024/06/27/s7/"/>
    <url>/2024/06/27/s7/</url>
    
    
    <categories>
      
      <category>文学</category>
      
      <category>诗词曲联</category>
      
    </categories>
    
    
    <tags>
      
      <tag>文学</tag>
      
      <tag>诗集</tag>
      
    </tags>
    
  </entry>
  
  
  
  <entry>
    <title>癸卯中秋清涵居士辞暮君上记载《清涵随文录》</title>
    <link href="/2024/06/27/wy7/"/>
    <url>/2024/06/27/wy7/</url>
    
    
    <categories>
      
      <category>文学</category>
      
      <category>文言</category>
      
    </categories>
    
    
    <tags>
      
      <tag>文学</tag>
      
      <tag>文言</tag>
      
    </tags>
    
  </entry>
  
  
  
  <entry>
    <title>无题诗</title>
    <link href="/2024/06/27/s5/"/>
    <url>/2024/06/27/s5/</url>
    
    
    <categories>
      
      <category>文学</category>
      
      <category>诗词曲联</category>
      
    </categories>
    
    
    <tags>
      
      <tag>文学</tag>
      
      <tag>诗集</tag>
      
    </tags>
    
  </entry>
  
  
  
  <entry>
    <title>偶逢</title>
    <link href="/2024/06/27/s6/"/>
    <url>/2024/06/27/s6/</url>
    
    
    <categories>
      
      <category>文学</category>
      
      <category>诗词曲联</category>
      
    </categories>
    
    
    <tags>
      
      <tag>文学</tag>
      
      <tag>诗集</tag>
      
    </tags>
    
  </entry>
  
  
  
  <entry>
    <title>八声甘州</title>
    <link href="/2024/06/27/s4/"/>
    <url>/2024/06/27/s4/</url>
    
    
    <categories>
      
      <category>文学</category>
      
      <category>诗词曲联</category>
      
    </categories>
    
    
    <tags>
      
      <tag>文学</tag>
      
      <tag>词集</tag>
      
    </tags>
    
  </entry>
  
  
  
  <entry>
    <title>如梦令</title>
    <link href="/2024/06/27/s3/"/>
    <url>/2024/06/27/s3/</url>
    
    
    <categories>
      
      <category>文学</category>
      
      <category>诗词曲联</category>
      
    </categories>
    
    
    <tags>
      
      <tag>文学</tag>
      
      <tag>词集</tag>
      
    </tags>
    
  </entry>
  
  
  
  <entry>
    <title>荒乱-第十九章</title>
    <link href="/2024/06/26/hl19/"/>
    <url>/2024/06/26/hl19/</url>
    
    
    <categories>
      
      <category>文学</category>
      
      <category>祅事书记</category>
      
      <category>荒乱</category>
      
    </categories>
    
    
    <tags>
      
      <tag>文学</tag>
      
      <tag>叙事</tag>
      
    </tags>
    
  </entry>
  
  
  
  <entry>
    <title>荒乱-第十八章</title>
    <link href="/2024/06/26/hl18/"/>
    <url>/2024/06/26/hl18/</url>
    
    
    <categories>
      
      <category>文学</category>
      
      <category>祅事书记</category>
      
      <category>荒乱</category>
      
    </categories>
    
    
    <tags>
      
      <tag>文学</tag>
      
      <tag>叙事</tag>
      
    </tags>
    
  </entry>
  
  
  
  <entry>
    <title>荒乱-第十七章</title>
    <link href="/2024/06/26/hl17/"/>
    <url>/2024/06/26/hl17/</url>
    
    
    <categories>
      
      <category>文学</category>
      
      <category>祅事书记</category>
      
      <category>荒乱</category>
      
    </categories>
    
    
    <tags>
      
      <tag>文学</tag>
      
      <tag>叙事</tag>
      
    </tags>
    
  </entry>
  
  
  
  <entry>
    <title>荒乱-第十六章</title>
    <link href="/2024/06/26/hl16/"/>
    <url>/2024/06/26/hl16/</url>
    
    
    <categories>
      
      <category>文学</category>
      
      <category>祅事书记</category>
      
      <category>荒乱</category>
      
    </categories>
    
    
    <tags>
      
      <tag>文学</tag>
      
      <tag>叙事</tag>
      
    </tags>
    
  </entry>
  
  
  
  <entry>
    <title>荒乱-第十五章</title>
    <link href="/2024/06/26/hl15/"/>
    <url>/2024/06/26/hl15/</url>
    
    
    <categories>
      
      <category>文学</category>
      
      <category>祅事书记</category>
      
      <category>荒乱</category>
      
    </categories>
    
    
    <tags>
      
      <tag>文学</tag>
      
      <tag>叙事</tag>
      
    </tags>
    
  </entry>
  
  
  
  <entry>
    <title>荒乱-第十四章</title>
    <link href="/2024/06/26/hl14/"/>
    <url>/2024/06/26/hl14/</url>
    
    
    <categories>
      
      <category>文学</category>
      
      <category>祅事书记</category>
      
      <category>荒乱</category>
      
    </categories>
    
    
    <tags>
      
      <tag>文学</tag>
      
      <tag>叙事</tag>
      
    </tags>
    
  </entry>
  
  
  
  <entry>
    <title>荒乱-第十三章</title>
    <link href="/2024/06/26/hl13/"/>
    <url>/2024/06/26/hl13/</url>
    
    
    <categories>
      
      <category>文学</category>
      
      <category>祅事书记</category>
      
      <category>荒乱</category>
      
    </categories>
    
    
    <tags>
      
      <tag>文学</tag>
      
      <tag>叙事</tag>
      
    </tags>
    
  </entry>
  
  
  
  <entry>
    <title>荒乱-第十二章</title>
    <link href="/2024/06/26/hl12/"/>
    <url>/2024/06/26/hl12/</url>
    
    
    <categories>
      
      <category>文学</category>
      
      <category>祅事书记</category>
      
      <category>荒乱</category>
      
    </categories>
    
    
    <tags>
      
      <tag>文学</tag>
      
      <tag>叙事</tag>
      
    </tags>
    
  </entry>
  
  
  
  <entry>
    <title>荒乱-第十一章</title>
    <link href="/2024/06/26/hl11/"/>
    <url>/2024/06/26/hl11/</url>
    
    
    <categories>
      
      <category>文学</category>
      
      <category>祅事书记</category>
      
      <category>荒乱</category>
      
    </categories>
    
    
    <tags>
      
      <tag>文学</tag>
      
      <tag>叙事</tag>
      
    </tags>
    
  </entry>
  
  
  
  <entry>
    <title>荒乱-第十章</title>
    <link href="/2024/06/26/hl10/"/>
    <url>/2024/06/26/hl10/</url>
    
    
    <categories>
      
      <category>文学</category>
      
      <category>祅事书记</category>
      
      <category>荒乱</category>
      
    </categories>
    
    
    <tags>
      
      <tag>文学</tag>
      
      <tag>叙事</tag>
      
    </tags>
    
  </entry>
  
  
  
  <entry>
    <title>荒乱-第九章</title>
    <link href="/2024/06/26/hl9/"/>
    <url>/2024/06/26/hl9/</url>
    
    
    <categories>
      
      <category>文学</category>
      
      <category>祅事书记</category>
      
      <category>荒乱</category>
      
    </categories>
    
    
    <tags>
      
      <tag>文学</tag>
      
      <tag>叙事</tag>
      
    </tags>
    
  </entry>
  
  
  
  <entry>
    <title>荒乱-第八章</title>
    <link href="/2024/06/26/hl8/"/>
    <url>/2024/06/26/hl8/</url>
    
    
    <categories>
      
      <category>文学</category>
      
      <category>祅事书记</category>
      
      <category>荒乱</category>
      
    </categories>
    
    
    <tags>
      
      <tag>文学</tag>
      
      <tag>叙事</tag>
      
    </tags>
    
  </entry>
  
  
  
  <entry>
    <title>荒乱-第七章</title>
    <link href="/2024/06/26/hl7/"/>
    <url>/2024/06/26/hl7/</url>
    
    
    <categories>
      
      <category>文学</category>
      
      <category>祅事书记</category>
      
      <category>荒乱</category>
      
    </categories>
    
    
    <tags>
      
      <tag>文学</tag>
      
      <tag>叙事</tag>
      
    </tags>
    
  </entry>
  
  
  
  <entry>
    <title>荒乱-第六章</title>
    <link href="/2024/06/26/hl6/"/>
    <url>/2024/06/26/hl6/</url>
    
    
    <categories>
      
      <category>文学</category>
      
      <category>祅事书记</category>
      
      <category>荒乱</category>
      
    </categories>
    
    
    <tags>
      
      <tag>文学</tag>
      
      <tag>叙事</tag>
      
    </tags>
    
  </entry>
  
  
  
  <entry>
    <title>荒乱-第五章</title>
    <link href="/2024/06/26/hl5/"/>
    <url>/2024/06/26/hl5/</url>
    
    
    <categories>
      
      <category>文学</category>
      
      <category>祅事书记</category>
      
      <category>荒乱</category>
      
    </categories>
    
    
    <tags>
      
      <tag>文学</tag>
      
      <tag>叙事</tag>
      
    </tags>
    
  </entry>
  
  
  
  <entry>
    <title>荒乱-第四章</title>
    <link href="/2024/06/26/hl4/"/>
    <url>/2024/06/26/hl4/</url>
    
    
    <categories>
      
      <category>文学</category>
      
      <category>祅事书记</category>
      
      <category>荒乱</category>
      
    </categories>
    
    
    <tags>
      
      <tag>文学</tag>
      
      <tag>叙事</tag>
      
    </tags>
    
  </entry>
  
  
  
  <entry>
    <title>荒乱-第三章</title>
    <link href="/2024/06/26/hl3/"/>
    <url>/2024/06/26/hl3/</url>
    
    
    <categories>
      
      <category>文学</category>
      
      <category>祅事书记</category>
      
      <category>荒乱</category>
      
    </categories>
    
    
    <tags>
      
      <tag>文学</tag>
      
      <tag>叙事</tag>
      
    </tags>
    
  </entry>
  
  
  
  <entry>
    <title>荒乱-第二章</title>
    <link href="/2024/06/25/hl2/"/>
    <url>/2024/06/25/hl2/</url>
    
    
    <categories>
      
      <category>文学</category>
      
      <category>祅事书记</category>
      
      <category>荒乱</category>
      
    </categories>
    
    
    <tags>
      
      <tag>文学</tag>
      
      <tag>叙事</tag>
      
    </tags>
    
  </entry>
  
  
  
  <entry>
    <title>荒乱-第一章</title>
    <link href="/2024/06/25/hl/"/>
    <url>/2024/06/25/hl/</url>
    
    
    <categories>
      
      <category>文学</category>
      
      <category>祅事书记</category>
      
      <category>荒乱</category>
      
    </categories>
    
    
    <tags>
      
      <tag>文学</tag>
      
      <tag>叙事</tag>
      
    </tags>
    
  </entry>
  
  
  
  <entry>
    <title>gif</title>
    <link href="/2024/06/21/dh/"/>
    <url>/2024/06/21/dh/</url>
    
    
    
    <tags>
      
      <tag>gif</tag>
      
    </tags>
    
  </entry>
  
  
  
  <entry>
    <title>极值-最值</title>
    <link href="/2024/06/17/sx3/"/>
    <url>/2024/06/17/sx3/</url>
    
    
    <categories>
      
      <category>数学</category>
      
      <category>奇技淫巧</category>
      
    </categories>
    
    
    <tags>
      
      <tag>数学</tag>
      
    </tags>
    
  </entry>
  
  
  
  <entry>
    <title>Minecraft-java-Forge-mod开发</title>
    <link href="/2024/06/11/mcjava/"/>
    <url>/2024/06/11/mcjava/</url>
    
    
    <categories>
      
      <category>技术</category>
      
    </categories>
    
    
    <tags>
      
      <tag>备忘录</tag>
      
    </tags>
    
  </entry>
  
  
  
  <entry>
    <title>数非角</title>
    <link href="/2024/06/10/wy6/"/>
    <url>/2024/06/10/wy6/</url>
    
    
    <categories>
      
      <category>文学</category>
      
      <category>文言</category>
      
      <category>讨论</category>
      
    </categories>
    
    
    <tags>
      
      <tag>文学</tag>
      
      <tag>文言</tag>
      
    </tags>
    
  </entry>
  
  
  
  <entry>
    <title>Python Tkinter汇总介绍</title>
    <link href="/2024/06/09/py/"/>
    <url>/2024/06/09/py/</url>
    
    
    <categories>
      
      <category>技术</category>
      
    </categories>
    
    
    <tags>
      
      <tag>备忘录</tag>
      
    </tags>
    
  </entry>
  
  
  
  <entry>
    <title>Python内置函数</title>
    <link href="/2024/06/09/py2/"/>
    <url>/2024/06/09/py2/</url>
    
    
    <categories>
      
      <category>技术</category>
      
    </categories>
    
    
    <tags>
      
      <tag>备忘录</tag>
      
    </tags>
    
  </entry>
  
  
  
  <entry>
    <title>空间中三角形四心</title>
    <link href="/2024/05/30/sx2/"/>
    <url>/2024/05/30/sx2/</url>
    
    
    <categories>
      
      <category>数学</category>
      
      <category>奇技淫巧</category>
      
    </categories>
    
    
    <tags>
      
      <tag>数学</tag>
      
    </tags>
    
  </entry>
  
  
  
  <entry>
    <title>小六壬</title>
    <link href="/2024/05/28/sg/"/>
    <url>/2024/05/28/sg/</url>
    
    
    <categories>
      
      <category>文学</category>
      
      <category>封建迷信</category>
      
    </categories>
    
    
    <tags>
      
      <tag>封建迷信</tag>
      
    </tags>
    
  </entry>
  
  
  
  <entry>
    <title>紫微斗数</title>
    <link href="/2024/05/28/sg2/"/>
    <url>/2024/05/28/sg2/</url>
    
    
    <categories>
      
      <category>文学</category>
      
      <category>封建迷信</category>
      
    </categories>
    
    
    <tags>
      
      <tag>封建迷信</tag>
      
    </tags>
    
  </entry>
  
  
  
  <entry>
    <title>无律诗集一</title>
    <link href="/2024/05/28/s2/"/>
    <url>/2024/05/28/s2/</url>
    
    
    <categories>
      
      <category>文学</category>
      
      <category>诗词曲联</category>
      
    </categories>
    
    
    <tags>
      
      <tag>文学</tag>
      
      <tag>诗集</tag>
      
    </tags>
    
  </entry>
  
  
  
  <entry>
    <title>向量-导数求解初中几何题</title>
    <link href="/2024/05/27/sx/"/>
    <url>/2024/05/27/sx/</url>
    
    
    <categories>
      
      <category>数学</category>
      
      <category>奇技淫巧</category>
      
    </categories>
    
    
    <tags>
      
      <tag>数学</tag>
      
    </tags>
    
  </entry>
  
  
  
  <entry>
    <title>杂剧-无名</title>
    <link href="/2024/05/27/yq/"/>
    <url>/2024/05/27/yq/</url>
    
    
    <categories>
      
      <category>文学</category>
      
      <category>诗词曲联</category>
      
    </categories>
    
    
    <tags>
      
      <tag>文学</tag>
      
      <tag>叙事</tag>
      
      <tag>杂剧</tag>
      
    </tags>
    
  </entry>
  
  
  
  <entry>
    <title>词集一</title>
    <link href="/2024/05/27/c/"/>
    <url>/2024/05/27/c/</url>
    
    
    <categories>
      
      <category>文学</category>
      
      <category>诗词曲联</category>
      
    </categories>
    
    
    <tags>
      
      <tag>文学</tag>
      
      <tag>词集</tag>
      
    </tags>
    
  </entry>
  
  
  
  <entry>
    <title>予且曲中外</title>
    <link href="/2024/05/27/wy5/"/>
    <url>/2024/05/27/wy5/</url>
    
    
    <categories>
      
      <category>文学</category>
      
      <category>祅事书记</category>
      
      <category>文言</category>
      
      <category>曲中外</category>
      
    </categories>
    
    
    <tags>
      
      <tag>文学</tag>
      
      <tag>文言</tag>
      
    </tags>
    
  </entry>
  
  
  
  <entry>
    <title>鸳怨误</title>
    <link href="/2024/05/27/xs/"/>
    <url>/2024/05/27/xs/</url>
    
    
    <categories>
      
      <category>文学</category>
      
      <category>祅事书记</category>
      
      <category>鸳怨误</category>
      
    </categories>
    
    
    <tags>
      
      <tag>文学</tag>
      
      <tag>叙事</tag>
      
    </tags>
    
  </entry>
  
  
  
  <entry>
    <title>鸿妖</title>
    <link href="/2024/05/27/sbx5/"/>
    <url>/2024/05/27/sbx5/</url>
    
    
    <categories>
      
      <category>文学</category>
      
      <category>祅事书记</category>
      
      <category>妖鬼</category>
      
    </categories>
    
    
    <tags>
      
      <tag>文学</tag>
      
      <tag>叙事</tag>
      
    </tags>
    
  </entry>
  
  
  
  <entry>
    <title>地府体系介绍</title>
    <link href="/2024/05/27/cs/"/>
    <url>/2024/05/27/cs/</url>
    
    
    <categories>
      
      <category>文学</category>
      
      <category>常识</category>
      
    </categories>
    
    
    <tags>
      
      <tag>文学常识</tag>
      
    </tags>
    
  </entry>
  
  
  
  <entry>
    <title>寒妖</title>
    <link href="/2024/05/27/sbx4/"/>
    <url>/2024/05/27/sbx4/</url>
    
    
    <categories>
      
      <category>文学</category>
      
      <category>祅事书记</category>
      
      <category>妖鬼</category>
      
    </categories>
    
    
    <tags>
      
      <tag>文学</tag>
      
      <tag>叙事</tag>
      
    </tags>
    
  </entry>
  
  
  
  <entry>
    <title>殣鬼</title>
    <link href="/2024/05/25/sbx3/"/>
    <url>/2024/05/25/sbx3/</url>
    
    
    <categories>
      
      <category>文学</category>
      
      <category>祅事书记</category>
      
      <category>妖鬼</category>
      
    </categories>
    
    
    <tags>
      
      <tag>文学</tag>
      
      <tag>叙事</tag>
      
    </tags>
    
  </entry>
  
  
  
  <entry>
    <title>暵妖</title>
    <link href="/2024/05/25/sbx2/"/>
    <url>/2024/05/25/sbx2/</url>
    
    
    <categories>
      
      <category>文学</category>
      
      <category>祅事书记</category>
      
      <category>妖鬼</category>
      
    </categories>
    
    
    <tags>
      
      <tag>文学</tag>
      
      <tag>叙事</tag>
      
    </tags>
    
  </entry>
  
  
  
  <entry>
    <title>书生与女子</title>
    <link href="/2024/05/25/sbx/"/>
    <url>/2024/05/25/sbx/</url>
    
    
    <categories>
      
      <category>文学</category>
      
      <category>祅事书记</category>
      
      <category>妖鬼</category>
      
    </categories>
    
    
    <tags>
      
      <tag>文学</tag>
      
      <tag>叙事</tag>
      
    </tags>
    
  </entry>
  
  
  
  <entry>
    <title>朝堂记</title>
    <link href="/2024/05/25/wy4/"/>
    <url>/2024/05/25/wy4/</url>
    
    
    <categories>
      
      <category>文学</category>
      
      <category>祅事书记</category>
      
      <category>文言</category>
      
      <category>朝堂</category>
      
    </categories>
    
    
    <tags>
      
      <tag>文学</tag>
      
      <tag>叙事</tag>
      
      <tag>文言</tag>
      
    </tags>
    
  </entry>
  
  
  
  <entry>
    <title>数非虚</title>
    <link href="/2024/05/25/wy3/"/>
    <url>/2024/05/25/wy3/</url>
    
    
    <categories>
      
      <category>文学</category>
      
      <category>文言</category>
      
      <category>讨论</category>
      
    </categories>
    
    
    <tags>
      
      <tag>文学</tag>
      
      <tag>文言</tag>
      
    </tags>
    
  </entry>
  
  
  
  <entry>
    <title>言“毛遂自荐，人须争锋”</title>
    <link href="/2024/05/25/wy2/"/>
    <url>/2024/05/25/wy2/</url>
    
    
    <categories>
      
      <category>文学</category>
      
      <category>文言</category>
      
      <category>讨论</category>
      
    </categories>
    
    
    <tags>
      
      <tag>文学</tag>
      
      <tag>文言</tag>
      
    </tags>
    
  </entry>
  
  
  
  <entry>
    <title>言“木秀于林，风则摧之”</title>
    <link href="/2024/05/25/wy/"/>
    <url>/2024/05/25/wy/</url>
    
    
    <categories>
      
      <category>文学</category>
      
      <category>文言</category>
      
      <category>讨论</category>
      
    </categories>
    
    
    <tags>
      
      <tag>文学</tag>
      
      <tag>文言</tag>
      
    </tags>
    
  </entry>
  
  
  
  <entry>
    <title>诗集一</title>
    <link href="/2024/05/25/s/"/>
    <url>/2024/05/25/s/</url>
    
    
    <categories>
      
      <category>文学</category>
      
      <category>诗词曲联</category>
      
    </categories>
    
    
    <tags>
      
      <tag>文学</tag>
      
      <tag>诗集</tag>
      
    </tags>
    
  </entry>
  
  
  
  <entry>
    <title>对联集一</title>
    <link href="/2024/05/25/dl/"/>
    <url>/2024/05/25/dl/</url>
    
    
    <categories>
      
      <category>文学</category>
      
      <category>诗词曲联</category>
      
    </categories>
    
    
    <tags>
      
      <tag>文学</tag>
      
      <tag>对联集</tag>
      
    </tags>
    
  </entry>
  
  
  
  
</search>
